{
    "artists": [
        {
            "attribute-list": [
                "nai", 
                "solo"
            ], 
            "mbid": "3a57e3a4-4e48-4ce2-aae0-c5b5275721eb", 
            "name": "Salih Bilgin", 
            "type": "instrument"
        }
    ], 
    "mbid": "fa022d35-6948-4ba7-95e8-7c63226e7502", 
    "tags": {
        "form": "sazsemaisi", 
        "makam": "muhayyer"
    }, 
    "title": "Muhayyer Saz Semai (Kiz Ney)", 
    "works": [
        {
            "artists": [
                {
                    "mbid": "4cc5200e-a3f7-4d5d-8b15-9b10a8f9a9a2", 
                    "name": "Tanburi Cemil Bey", 
                    "type": "composer"
                }
            ], 
            "mbid": "ac003195-9ea0-4d8e-8420-2d6c269e98f6", 
            "score": {
                "name": "muhayyer--sazsemaisi--aksaksemai----tanburi_cemil_bey", 
                "type": "symbTr_v2"
            }, 
            "title": "Muhayyer Sazsemaisi"
        }
    ]
}