{
    "artists": [
        {
            "attribute-list": [], 
            "mbid": "", 
            "name": "", 
            "type": ""
        }
    ], 
    "mbid": "c0af7cc9-af66-4115-94de-7255cf1a44b2", 
    "tags": {
        "form": "sazsemaisi", 
        "makam": "sultaniyegah", 
        "usul": "aksaksemai"
    }, 
    "title": "Sultaniyegah Saz Semaisi", 
    "works": [
        {
            "artists": [
                {
                    "mbid": "f27dbcf2-0be7-4951-a981-dd2b88e70565", 
                    "name": "Nedim Aga", 
                    "type": "composer"
                }
            ], 
            "mbid": "ecf1b766-6d29-4d13-9fc8-4c02c38d4263", 
            "score": {
                "name": "", 
                "type": "symbTr_v2"
            }, 
            "title": "Sultaniyegah Sazsemaisi"
        }
    ]
}