{
    "artists": [
        {
            "attribute-list": [], 
            "mbid": "", 
            "name": "", 
            "type": ""
        }
    ], 
    "mbid": "01b485c1-4c1a-4916-b8a5-1ec913da1c45", 
    "tags": {
        "form": "pe\u015frev", 
        "makam": "k\u00fcrdilihicazkar"
    }, 
    "title": "Kurdilihicazkar Pesrev", 
    "works": [
        {
            "artists": [
                {
                    "mbid": "e3d3f39f-f597-41c6-858d-e04b6ecd65c3", 
                    "name": "Vasilaki Efendi", 
                    "type": "composer"
                }
            ], 
            "mbid": "e3691957-a2bd-4e40-8041-582af3a02b4e", 
            "score": {
                "name": "kurdilihicazkar--pesrev--agirduyek----vasilaki", 
                "type": "symbTr_v2"
            }, 
            "title": "Kurdilihicazkar Pesrev"
        }
    ]
}