{
    "artists": [
        {
            "attribute-list": [], 
            "mbid": "", 
            "name": "", 
            "type": ""
        }
    ], 
    "mbid": "7d3a46a3-52c8-4dbe-8c60-bc14ac8e5a09", 
    "tags": {
        "form": "pe\u015frev", 
        "makam": "k\u00fcrdilihicazkar", 
        "usul": "devr-i kebir"
    }, 
    "title": "Kurdili Hicazkar Pesrev", 
    "works": [
        {
            "artists": [
                {
                    "mbid": "9157531e-ba32-46e7-8c60-1a66c99f2ace", 
                    "name": "Tateos Enserciyan", 
                    "type": "composer"
                }
            ], 
            "mbid": "caf01faf-7e0e-4463-ac27-6d56c9055434", 
            "score": {
                "name": "", 
                "type": "symbTr_v2"
            }, 
            "title": "Kurdilihicazkar Pesrev"
        }
    ]
}