{
    "artists": [
        {
            "attribute-list": [
                "tanbur"
            ], 
            "mbid": "9b6e98f8-b695-45da-8c9c-68d4bab460fd", 
            "name": "Murat Aydemir", 
            "type": "instrument"
        }
    ], 
    "mbid": "e2fdd872-38db-4f71-88de-f6a7f0c8f02a", 
    "tags": {
        "form": "sazsemaisi", 
        "makam": "beyati", 
        "usul": "aksaksemai"
    }, 
    "title": "Beyati Sazsemaisi", 
    "works": [
        {
            "artists": [
                {
                    "mbid": "2871a8ff-e2fa-4568-9562-0a5e3fe57330", 
                    "name": "Kanuni Omer Efendi", 
                    "type": "composer"
                }
            ], 
            "mbid": "fac99291-4c31-416b-af9b-4282fb5ca1e8", 
            "score": {
                "name": "beyati--sazsemaisi--aksaksemai----kanuni_omer_efendi", 
                "type": "symbTr_v2"
            }, 
            "title": "Beyati Sazsemaisi"
        }
    ]
}