{
    "artists": [
        {
            "attribute-list": [], 
            "mbid": "", 
            "name": "", 
            "type": ""
        }
    ], 
    "mbid": "7d2cb4b1-11e6-470b-ab63-bfa92be39050", 
    "tags": {
        "form": "sazsemaisi", 
        "makam": "neveser", 
        "usul": "aksaksemai"
    }, 
    "title": "Nev'eser Sazsemaisi", 
    "works": [
        {
            "artists": [
                {
                    "mbid": "463196f6-9604-49e6-afa2-f6bde8b1c1a9", 
                    "name": "Neyzen Yusuf Pasa", 
                    "type": "composer"
                }
            ], 
            "mbid": "33fbe40b-15c8-410a-97d9-3f80c341159d", 
            "score": {
                "name": "", 
                "type": "symbTr_v2"
            }, 
            "title": "Nev'eser Saz Semaisi"
        }
    ]
}